odoo10_addon_mail_environment-10.0.1.0.0.99.dev11-py2.7-nspkg.pth
odoo/addons/mail_environment/README.rst
odoo/addons/mail_environment/__init__.py
odoo/addons/mail_environment/__manifest__.py
odoo/addons/mail_environment/i18n/de.po
odoo/addons/mail_environment/i18n/es.po
odoo/addons/mail_environment/i18n/hr.po
odoo/addons/mail_environment/i18n/it.po
odoo/addons/mail_environment/i18n/mail_environment.pot
odoo/addons/mail_environment/i18n/pt_BR.po
odoo/addons/mail_environment/i18n/sl.po
odoo/addons/mail_environment/i18n/zh_CN.po
odoo/addons/mail_environment/models/__init__.py
odoo/addons/mail_environment/models/fetchmail_server.py
odoo/addons/mail_environment/models/ir_mail_server.py
odoo/addons/mail_environment/views/fetchmail_server_views.xml
odoo10_addon_mail_environment-10.0.1.0.0.99.dev11.dist-info/METADATA
odoo10_addon_mail_environment-10.0.1.0.0.99.dev11.dist-info/RECORD
odoo10_addon_mail_environment-10.0.1.0.0.99.dev11.dist-info/WHEEL
odoo10_addon_mail_environment-10.0.1.0.0.99.dev11.dist-info/namespace_packages.txt
odoo10_addon_mail_environment-10.0.1.0.0.99.dev11.dist-info/top_level.txt
