Metadata-Version: 2.1
Name: odoo10-addon-mail-environment
Version: 10.0.1.0.0.99.dev11
Summary: Configure mail servers with server_environment_files
Home-page: http://odoo-community.org
Author: Camptocamp,Odoo Community Association (OCA)
Author-email: support@odoo-community.org
License: AGPL-3
Platform: UNKNOWN
Classifier: Programming Language :: Python
Classifier: Framework :: Odoo
Classifier: License :: OSI Approved :: GNU Affero General Public License v3
Requires-Python: ~=2.7
Requires-Dist: odoo10-addon-server-environment
Requires-Dist: odoo (<10.1dev,>=10.0)
